netget/__init__.py
netget_me-0.1.0.dist-info/METADATA
netget_me-0.1.0.dist-info/WHEEL
netget_me-0.1.0.dist-info/top_level.txt
netget_me-0.1.0.dist-info/RECORD
